nelltest
