Metadata-Version: 2.1
Name: nelltest
Version: 0.2.2
Summary: Debugged
Home-page: UNKNOWN
Author-email: elezor.2009@gmail.com
License: UNKNOWN
Platform: UNKNOWN
